minimax_qa_mcp/__init__.py
minimax_qa_mcp/server.py
minimax_qa_mcp/conf/__init__.py
minimax_qa_mcp/conf/conf.ini
minimax_qa_mcp/src/__init__.py
minimax_qa_mcp/src/auto_case/__init__.py
minimax_qa_mcp/src/auto_case/case_write.py
minimax_qa_mcp/src/auto_case/pdf_jiexi.py
minimax_qa_mcp/src/gateway_case/__init__.py
minimax_qa_mcp/src/gateway_case/get_case.py
minimax_qa_mcp/src/generator_case/__init__.py
minimax_qa_mcp/src/generator_case/generator_case.py
minimax_qa_mcp/src/generator_case/generator_case_langchain.py
minimax_qa_mcp/src/get_full_api_call_chain/__init__.py
minimax_qa_mcp/src/get_full_api_call_chain/get_full_api_call_chain.py
minimax_qa_mcp/src/get_weaviate_info/__init__.py
minimax_qa_mcp/src/get_weaviate_info/get_weaviate_info.py
minimax_qa_mcp/src/grafana/__init__.py
minimax_qa_mcp/src/grafana/service.py
minimax_qa_mcp/src/query_segments/__init__.py
minimax_qa_mcp/src/query_segments/query_segments.py
minimax_qa_mcp/src/xmind2markdown/__init__.py
minimax_qa_mcp/src/xmind2markdown/xmind_to_markdown.py
minimax_qa_mcp/utils/__init__.py
minimax_qa_mcp/utils/logger.py
minimax_qa_mcp/utils/mysql_op.py
minimax_qa_mcp/utils/utils.py
mm_qa_mcp-3.0.3.dist-info/METADATA
mm_qa_mcp-3.0.3.dist-info/WHEEL
mm_qa_mcp-3.0.3.dist-info/entry_points.txt
mm_qa_mcp-3.0.3.dist-info/top_level.txt
mm_qa_mcp-3.0.3.dist-info/RECORD
