Metadata-Version: 2.4
Name: mm_qa_mcp
Version: 3.0.3
Summary: QA agent service 集合
Author-email: xingyun <xingyun@minimaxi.com>
License-Expression: MIT
Classifier: Development Status :: 4 - Beta
Classifier: Intended Audience :: Developers
Classifier: Programming Language :: Python :: 3
Classifier: Programming Language :: Python :: 3.9
Classifier: Programming Language :: Python :: 3.10
Requires-Python: >=3.10
Requires-Dist: pymysql>=1.1.1
Requires-Dist: annotated-types>=0.7.0
Requires-Dist: anyio>=4.9.0
Requires-Dist: Authlib<2.0.0,>=1.2.1
Requires-Dist: certifi>=2025.1.31
Requires-Dist: cffi>=1.17.1
Requires-Dist: charset-normalizer>=3.4.1
Requires-Dist: click>=8.1.8
Requires-Dist: cryptography>=44.0.2
Requires-Dist: h11>=0.14.0
Requires-Dist: httpcore>=1.0.7
Requires-Dist: httpx>=0.28.1
Requires-Dist: httpx-sse>=0.4.0
Requires-Dist: idna>=3.10
Requires-Dist: jsonpatch>=1.33
Requires-Dist: jsonpointer>=3.0.0
Requires-Dist: langchain-core>=0.3.51
Requires-Dist: langsmith>=0.3.27
Requires-Dist: mcp>=1.6.0
Requires-Dist: numpy>=2.2.4
Requires-Dist: orjson>=3.10.16
Requires-Dist: packaging>=24.2
Requires-Dist: pandas>=2.2.3
Requires-Dist: prettytable>=3.16.0
Requires-Dist: pycparser>=2.22
Requires-Dist: pydantic>=2.11.3
Requires-Dist: pydantic-settings>=2.8.1
Requires-Dist: pydantic_core>=2.33.1
Requires-Dist: python-dateutil>=2.9.0.post0
Requires-Dist: python-dotenv>=1.1.0
Requires-Dist: pytz>=2025.2
Requires-Dist: PyYAML>=6.0.2
Requires-Dist: requests<3.0.0,>=2.30.0
Requires-Dist: requests-toolbelt>=1.0.0
Requires-Dist: six>=1.17.0
Requires-Dist: sniffio>=1.3.1
Requires-Dist: sse-starlette>=2.2.1
Requires-Dist: starlette>=0.46.1
Requires-Dist: tabulate>=0.9.0
Requires-Dist: tenacity>=9.1.2
Requires-Dist: typing-inspection>=0.4.0
Requires-Dist: typing_extensions>=4.13.1
Requires-Dist: tzdata>=2025.2
Requires-Dist: urllib3<3.0.0,>=1.21.1
Requires-Dist: uvicorn>=0.34.0
Requires-Dist: validators<1.0.0,>=0.21.2
Requires-Dist: wcwidth>=0.2.13
Requires-Dist: weaviate-client<4.0.0,>=3.25.0
Requires-Dist: zstandard>=0.23.0
Requires-Dist: pdfplumber>=0.11.6
Provides-Extra: dev
Requires-Dist: pytest>=7.0.0; extra == "dev"
Requires-Dist: mypy>=1.0.0; extra == "dev"
Requires-Dist: black>=23.0.0; extra == "dev"
Requires-Dist: isort>=5.12.0; extra == "dev"
Requires-Dist: twine>=4.0.0; extra == "dev"
